{
  "completed": "2023-08-30T07:47:58.709039Z",
  "periodic": true,
  "started": "2023-08-30T07:47:56.562229Z",
  "versions": [
    {
      "filename": "wheel-0.41.2-py3-none-any.whl",
      "found_date": "2023-08-30T07:47:56.621949Z",
      "release_date": "2023-08-22T09:30:57.000000Z",
      "source": "periodic"
    },
    {
      "filename": "wheel-0.41.1-py3-none-any.whl",
      "found_date": "2023-08-30T07:47:57.690015Z",
      "release_date": "2023-08-05T13:33:15.000000Z",
      "source": "periodic"
    }
  ]
}